mkdocs_ultralytics_plugin-0.2.4.dist-info/licenses/LICENSE
plugin/__init__.py
plugin/main.py
plugin/postprocess.py
plugin/processor.py
plugin/utils.py
mkdocs_ultralytics_plugin-0.2.4.dist-info/METADATA
mkdocs_ultralytics_plugin-0.2.4.dist-info/WHEEL
mkdocs_ultralytics_plugin-0.2.4.dist-info/entry_points.txt
mkdocs_ultralytics_plugin-0.2.4.dist-info/top_level.txt
mkdocs_ultralytics_plugin-0.2.4.dist-info/RECORD
