Metadata-Version: 2.4
Name: mkdocs-ultralytics-plugin
Version: 0.2.4
Summary: An MkDocs plugin that provides Ultralytics Docs customizations at https://docs.ultralytics.com.
Author-email: Glenn Jocher <hello@ultralytics.com>
Maintainer-email: Ultralytics <hello@ultralytics.com>
License: AGPL-3.0
Project-URL: Homepage, https://ultralytics.com
Project-URL: Source, https://github.com/ultralytics/mkdocs
Project-URL: Documentation, https://docs.ultralytics.com
Project-URL: Bug Reports, https://github.com/ultralytics/mkdocs/issues
Project-URL: Changelog, https://github.com/ultralytics/mkdocs/releases
Keywords: Ultralytics,Docs,MkDocs,Plugin
Classifier: Development Status :: 4 - Beta
Classifier: Intended Audience :: Developers
Classifier: Intended Audience :: Education
Classifier: Intended Audience :: Science/Research
Classifier: License :: OSI Approved :: GNU Affero General Public License v3 or later (AGPLv3+)
Classifier: Programming Language :: Python :: 3
Classifier: Programming Language :: Python :: 3.8
Classifier: Programming Language :: Python :: 3.9
Classifier: Programming Language :: Python :: 3.10
Classifier: Programming Language :: Python :: 3.11
Classifier: Programming Language :: Python :: 3.12
Classifier: Programming Language :: Python :: 3.13
Classifier: Programming Language :: Python :: 3.14
Classifier: Topic :: Software Development
Classifier: Topic :: Scientific/Engineering
Classifier: Topic :: Scientific/Engineering :: Artificial Intelligence
Classifier: Operating System :: POSIX :: Linux
Classifier: Operating System :: MacOS
Classifier: Operating System :: Microsoft :: Windows
Requires-Python: >=3.8
License-File: LICENSE
Requires-Dist: mkdocs>=1.0
Requires-Dist: beautifulsoup4>=4.13.5
Requires-Dist: pyyaml
Requires-Dist: requests>=2.28.1
Provides-Extra: dev
Requires-Dist: pytest; extra == "dev"
Dynamic: license-file
